AUTHORS.txt
CHANGES.rst
CLASSIFIERS.txt
MANIFEST.in
README.rst
REQUIREMENTS.txt
setup.py
flask_easylog/__init__.py
flask_easylog/api.py
flask_easylog/plugin.py
flask_easylog/ui.py
flask_easylog/util.py
flask_easylog.egg-info/PKG-INFO
flask_easylog.egg-info/SOURCES.txt
flask_easylog.egg-info/dependency_links.txt
flask_easylog.egg-info/not-zip-safe
flask_easylog.egg-info/requires.txt
flask_easylog.egg-info/top_level.txt
flask_easylog/ui/index.html
test/test_api.py
test/test_plugin.py
test/test_ui.py